GPyS/GPyS_LOOCV_error.py
GPyS/GPyS_prediction.py
GPyS/GPyS_preprocessor.py
GPyS/__init__.py
GPyS-0.1.2.dist-info/LICENSE
GPyS-0.1.2.dist-info/METADATA
GPyS-0.1.2.dist-info/WHEEL
GPyS-0.1.2.dist-info/top_level.txt
GPyS-0.1.2.dist-info/RECORD
