Metadata-Version: 2.1
Name: GPyS
Version: 0.1.2
Summary: Gaussian Process Subspace Prediction
Author-email: "ZHANG, Ruda" <rudaz@Central.UH.EDU>, Taiwo Adebiyi <taadebi2@cougarnet.uh.edu>
Project-URL: Homepage, https://github.com/UQUH/GPyS
Classifier: Programming Language :: Python :: 3
Classifier: License :: OSI Approved :: GNU General Public License v3 or later (GPLv3+)
Classifier: Operating System :: OS Independent
Requires-Python: >=3.10
License-File: LICENSE
